<configgroup name = "CALIBRATION_TABLE">
<configitem name="DESCRIPTION"><value>VDO PSI 150 MAX</value></configitem>
<configitem name="TYPE"><value>Pressure</value></configitem>
<configitem name="UNITS"><value>Pascal</value></configitem>
<configitem name="RESOLUTION"><value>4kPa</value></configitem>
<configitem name="MIN"><value>0</value></configitem>
<configitem name="MAX"><value>1034</value></configitem>
<configitem name="LOOKUPVALUES"><value>
000000,
000000,
000000,
000000,
000000,
000000,
000000,
000000,
000000,
000000,
000000,
000000,
000000,
000000,
000000,
000000,
000000,
000000,
000000,
000000,
000000,
000000,
000000,
000000,
000000,
000000,
000000,
000000,
000000,
000000,
000000,
000000,
000000,
000000,
000000,
000000,
000000,
000000,
000000,
000000,
000000,
000000,
000000,
000000,
000000,
000000,
000002,
000002,
000002,
000002,
000002,
000003,
000003,
000003,
000003,
000003,
000005,
000005,
000007,
000007,
000007,
000007,
000009,
000009,
000009,
000009,
000009,
000010,
000010,
000010,
000010,
000012,
000012,
000014,
000014,
000014,
000014,
000016,
000016,
000016,
000017,
000017,
000019,
000019,
000019,
000021,
000021,
000021,
000021,
000022,
000022,
000022,
000024,
000024,
000026,
000026,
000026,
000028,
000028,
000029,
000029,
000031,
000031,
000031,
000033,
000033,
000034,
000034,
000036,
000036,
000038,
000038,
000038,
000040,
000040,
000041,
000043,
000043,
000045,
000045,
000045,
000047,
000048,
000048,
000050,
000050,
000052,
000052,
000053,
000055,
000057,
000057,
000059,
000060,
000060,
000062,
000062,
000066,
000066,
000067,
000067,
000069,
000071,
000072,
000074,
000074,
000076,
000078,
000079,
000081,
000081,
000084,
000084,
000086,
000090,
000090,
000091,
000093,
000097,
000097,
000098,
000102,
000103,
000105,
000107,
000109,
000110,
000114,
000115,
000119,
000121,
000122,
000126,
000128,
000131,
000133,
000136,
000138,
000141,
000145,
000148,
000150,
000153,
000157,
000160,
000164,
000167,
000171,
000174,
000178,
000181,
000186,
000181,
000195,
000198,
000203,
000209,
000214,
000219,
000222,
000229,
000234,
000240,
000246,
000252,
000255,
000255,
000255,
000255,
000255,
000255,
000255,
000255,
000255,
000255,
000255,
000255,
000255,
000255,
000255,
000255,
000255,
000255,
000255,
000255,
000255,
000255,
000255,
000255,
000255,
000255,
000255,
000255,
000255,
000255,
000255,
000255,
000255,
000255,
000255,
000255,
000255,
000255,
000255,
000255,
000255,
000255,
000255,
000255,
000255,
000255,
000255,
000255,
000255,
000255,
000255,
</value></configitem>
</configgroup>